Metadata-Version: 2.1
Name: korokoro
Version: 0.27
Summary: A Python pingpong table Korean VS Romantic
Home-page: https://github.com/yoonhero/korona
Author: seonghyeon yoon
Author-email: yoonhero06@naver.com
License: GNU GPLv3
Keywords: Korean,Romanization,Transliteration
Classifier: Development Status :: 3 - Alpha
Classifier: Intended Audience :: Developers
Classifier: Topic :: Software Development :: Libraries :: Python Modules
Classifier: License :: OSI Approved :: GNU General Public License v3 or later (GPLv3+)
Classifier: Programming Language :: Python :: 3
Classifier: Programming Language :: Python :: 3.4
Classifier: Programming Language :: Python :: 3.5
Classifier: Programming Language :: Python :: 3.6
License-File: LICENSE
License-File: COPYING
